otel_analyzer_mcp/__init__.py
otel_analyzer_mcp/cloudwatch.py
otel_analyzer_mcp/models.py
otel_analyzer_mcp/parsers.py
otel_analyzer_mcp/server.py
otel_analyzer_mcp/xray.py
otel_analyzer_mcp/analyzers/__init__.py
otel_analyzer_mcp/analyzers/errors.py
otel_analyzer_mcp/analyzers/performance.py
otel_analyzer_mcp-0.1.1.dist-info/METADATA
otel_analyzer_mcp-0.1.1.dist-info/WHEEL
otel_analyzer_mcp-0.1.1.dist-info/entry_points.txt
otel_analyzer_mcp-0.1.1.dist-info/licenses/LICENSE
otel_analyzer_mcp-0.1.1.dist-info/RECORD
