Metadata-Version: 2.4
Name: otel-analyzer-mcp
Version: 0.1.1
Summary: MCP server for analyzing OpenTelemetry traces
Project-URL: Homepage, https://github.com/jsamuel1/otel-analyzer-mcp
Project-URL: Documentation, https://github.com/jsamuel1/otel-analyzer-mcp#readme
Project-URL: Repository, https://github.com/jsamuel1/otel-analyzer-mcp
Project-URL: Issues, https://github.com/jsamuel1/otel-analyzer-mcp/issues
Project-URL: PyPI, https://pypi.org/project/otel-analyzer-mcp/
Author-email: Joshua Samuel <sauhsoj@amazon.com>
License-Expression: MIT
License-File: LICENSE
Keywords: mcp,model-context-protocol,observability,opentelemetry,traces,xray
Classifier: Development Status :: 3 - Alpha
Classifier: Intended Audience :: Developers
Classifier: License :: OSI Approved :: MIT License
Classifier: Programming Language :: Python :: 3
Classifier: Programming Language :: Python :: 3.11
Classifier: Programming Language :: Python :: 3.12
Classifier: Programming Language :: Python :: 3.13
Classifier: Topic :: Software Development :: Libraries :: Python Modules
Requires-Python: >=3.11
Requires-Dist: boto3>=1.42.30
Requires-Dist: fastmcp<3,>=2.14
Requires-Dist: networkx>=3.6.1
Requires-Dist: opentelemetry-proto>=1.39.1
Requires-Dist: pydantic>=2.12.5
Provides-Extra: build
Requires-Dist: build>=1.0.0; extra == 'build'
Requires-Dist: twine>=4.0.0; extra == 'build'
Provides-Extra: dev
Requires-Dist: pytest-asyncio>=0.21.0; extra == 'dev'
Requires-Dist: pytest-cov>=4.0.0; extra == 'dev'
Requires-Dist: pytest>=7.0.0; extra == 'dev'
